<annotation>
	<folder>allimages</folder>
	<filename>armas (189).jpg</filename>
	<path>D:\EntornoTensorflow\RealTimeObjectDetection\Tensorflow\workspace\images\allimages\armas (189).jpg</path>
	<source>
		<database>Unknown</database>
	</source>
	<size>
		<width>876</width>
		<height>493</height>
		<depth>3</depth>
	</size>
	<segmented>0</segmented>
	<object>
		<name>Arma</name>
		<pose>Unspecified</pose>
		<truncated>0</truncated>
		<difficult>0</difficult>
		<bndbox>
			<xmin>537</xmin>
			<ymin>201</ymin>
			<xmax>581</xmax>
			<ymax>253</ymax>
		</bndbox>
	</object>
</annotation>
